SmartCI/__init__.py
SmartCI/__main__.py
SmartCI/common/__init__.py
SmartCI/common/dao/__init__.py
SmartCI/common/dao/project_dependencies_dao_base.py
SmartCI/common/dao/project_dependencies_dao_factory.py
SmartCI/common/dao/project_dependencies_dao_memory.py
SmartCI/common/dao/project_dependencies_dao_neo4j.py
SmartCI/common/database/__init__.py
SmartCI/common/database/enums/__init__.py
SmartCI/common/database/enums/db_types.py
SmartCI/common/database/enums/file_types.py
SmartCI/common/database/local_storage/__init__.py
SmartCI/common/database/neo4j/__init__.py
SmartCI/common/database/neo4j/dao/__init__.py
SmartCI/common/database/neo4j/dao/base_node.py
SmartCI/common/database/neo4j/dao/file_nodes.py
SmartCI/common/git_providers/__init__.py
SmartCI/common/git_providers/git_accessor.py
SmartCI/common/git_providers/gitlab_accessor.py
SmartCI/manager/__init__.py
SmartCI/manager/cli_manager.py
SmartCI/manager/config_manager.py
SmartCI/planner/__init__.py
SmartCI/planner/ci_planner.py
SmartCI/planner/commit_extractor.py
SmartCI/planner/config.py
SmartCI/planner/effected_files_extractor.py
SmartCI/planner/tests_files_extractor.py
SmartCI/planner/tests/__init__.py
SmartCI/planner/tests/test_planner.py
SmartCI/planner/types/__init__.py
SmartCI/planner/types/commit_changes.py
SmartCI/planner/types/git_diff_level.py
SmartCI/planner/types/moved_file.py
SmartCI/scanner/__init__.py
SmartCI/scanner/dependencies_parser.py
SmartCI/scanner/project_scanner.py
SmartCI/scanner/accessors/__init__.py
SmartCI/scanner/accessors/pydeps_accessor.py
SmartCI/scanner/tests/__init__.py
SmartCI/scanner/tests/test_pydeps_accessor.py
SmartCI-1.0.2b2.dist-info/LICENSE.txt
SmartCI-1.0.2b2.dist-info/METADATA
SmartCI-1.0.2b2.dist-info/WHEEL
SmartCI-1.0.2b2.dist-info/entry_points.txt
SmartCI-1.0.2b2.dist-info/top_level.txt
SmartCI-1.0.2b2.dist-info/RECORD
